{"iphone":{"free":[{"order":1,"name":"疯狂攀岩家","company":"Beijing Chukong Aipu Technology Co.,Ltd.","category":"Games"},{"order":2,"name":"Printer Pro for iPhone","company":"Igor Zhadanov","category":"Productivity"},{"order":3,"name":"天猫（淘宝商城）- 时尚购物，正品网购","company":"Zhejiang Taobao Mall Technology Co,Ltd.","category":"Lifestyle"},{"order":4,"name":"果粉社区 - 最有爱的果粉互助交友工具","company":"zhang jianheng","category":"News"},{"order":5,"name":"博雅德州扑克","company":"","category":""},{"order":6,"name":"Aerox","company":"Synoptical Studios Ltd","category":"Games"},{"order":7,"name":"图吧导航3D地图【全能导航|免费语音导航|免费电子眼播报|在线离线都能用】","company":"Beijing Mapbar Technology Co.,Ltd","category":"Navigation"},{"order":8,"name":"战争世界——为你的国家奋勇开战！","company":"Gameloft S.A.","category":"Games"},{"order":9,"name":"51信用卡管家","company":"Shanghai Xiaomai CO.LTD","category":"Finance"},{"order":10,"name":"博雅广东麻将","company":"Boyaa Interactive International Limited","category":"Games"},{"order":11,"name":"卧龙吟 豪华版","company":"Shanghai UQEE Network Co.,Ltd","category":"Games"},{"order":12,"name":"魔神契约：圣杯","company":"Shanghai Qianxiang Changda Internet Information Technology Development Co.,Ltd.","category":"Games"},{"order":13,"name":"幽灵船","company":"Beijing Qianxiang Wangjing Technology Development Co., Ltd","category":"Games"},{"order":14,"name":"小幺鸡大合体","company":"","category":""},{"order":15,"name":"将军 for iPhone","company":"","category":""},{"order":16,"name":"全球战争","company":"Beijing Qianxiang Wangjing Technology Development Co., Ltd","category":"Games"},{"order":17,"name":"博雅斗地主(支持蓝牙)","company":"","category":""},{"order":18,"name":"Phone+ 免费电话","company":"Guiyang Longmaster Information &amp; Technology Co.,Ltd.","category":"Social Networking"},{"order":19,"name":"悍将三国","company":"beijing zhancheng technology LLC","category":"Games"},{"order":20,"name":"优购MALL-时尚优质名品鞋服网购平台","company":"Belle E-Commerce(Shanghai) Co.,LTD","category":"Lifestyle"},{"order":21,"name":"JJ斗地主","company":"JJWorld(Beijing) network technology Co., LTD","category":"Games"},{"order":22,"name":"高德地图(免费导航版)","company":"AutoNavi Information Technology Co. Ltd.","category":"Navigation"},{"order":23,"name":"新浪彩票官方合作版","company":"weifa wu","category":"Lifestyle"},{"order":24,"name":"艺龙—酒店·机票·旅游","company":"Beijing eLong Information Technology Co., Ltd.","category":"Travel"},{"order":25,"name":"中彩手•彩票","company":"","category":""}],"grossing":[{"order":1,"name":"龙之力量","company":"","category":""},{"order":2,"name":"逆转三国","company":"","category":""},{"order":3,"name":"神仙道","company":"PinIdea Co., Ltd.","category":"Games"},{"order":4,"name":"雄霸天地(简体版)","company":"","category":""},{"order":5,"name":"忘仙HD","company":"","category":""},{"order":6,"name":"三国志ONLINE(中国版)","company":"","category":""},{"order":7,"name":"大掌门","company":"","category":""},{"order":8,"name":"图吧导航HD【3D地图|四核引擎|图算双显】最新版","company":"Beijing Mapbar Technology Co.,Ltd","category":"Navigation"},{"order":9,"name":"三国来了","company":"","category":""},{"order":10,"name":"战魂Online","company":"","category":""},{"order":11,"name":"博雅德州扑克","company":"","category":""},{"order":12,"name":"魔卡幻想","company":"iFree Studio Limited","category":"Games"},{"order":13,"name":"调教三国","company":"TipCat Interactive Inc.","category":"Games"},{"order":14,"name":"三分天下","company":"DOVO CO.,LTD","category":"Games"},{"order":15,"name":"拇指西游-五星豪华版","company":"","category":""},{"order":16,"name":"捕鱼达人2","company":"","category":""},{"order":17,"name":"凯立德移动导航系统 V9.1 路况版","company":"Careland Technology (shenzhen) Co.,Ltd,","category":"Navigation"},{"order":18,"name":"悍将三国","company":"beijing zhancheng technology LLC","category":"Games"},{"order":19,"name":"御龙战记","company":"","category":""},{"order":20,"name":"高德导航HD Autonavi Navigation","company":"AutoNavi Information Technology Co. Ltd.","category":"Navigation"},{"order":21,"name":"杀手2-影子阴谋","company":"Glu Games Inc","category":"Games"},{"order":22,"name":"植物大战僵尸","company":"","category":""},{"order":23,"name":"QQ御剑•飞流至尊版","company":"Wang Ruzhang","category":"Games"},{"order":24,"name":"神仙道HD","company":"PinIdea Co., Ltd.","category":"Games"},{"order":25,"name":"僵尸坞","company":"Gameloft S.A.","category":"Games"}],"paid":[{"order":1,"name":"Angry Birds Star Wars","company":"Rovio Entertainment Ltd","category":"Games"},{"order":2,"name":"图吧导航HD【3D地图|四核引擎|图算双显】最新版","company":"Beijing Mapbar Technology Co.,Ltd","category":"Navigation"},{"order":3,"name":"三国战记2—异闻录","company":"Shenzhen TeamTop3 Communication Technology Co.,Ltd","category":"Games"},{"order":4,"name":"手机铃音（随意换）","company":"Nanjing Imohoo Information Technology Co., Ltd.","category":"Utilities"},{"order":5,"name":"51信用卡管家Pro","company":"Shanghai Xiaomai CO.LTD","category":"Finance"},{"order":6,"name":"三国华容道","company":"tao sui","category":"Games"},{"order":7,"name":"Fruit Ninja","company":"Halfbrick","category":"Games"},{"order":8,"name":"鳄鱼小顽皮爱洗澡","company":"Walt Disney","category":"Games"},{"order":9,"name":"捕鱼大亨2-联机对战版","company":"Clifree Technology Limited","category":"Games"},{"order":10,"name":"宠物猎人G","company":"Lan hang technology .Co","category":"Games"},{"order":11,"name":"狂野飙车7：极速热力","company":"Gameloft S.A.","category":"Games"},{"order":12,"name":"宫爆老奶奶","company":"BLUEFIR MEDIA CO. LIMITED","category":"Games"},{"order":13,"name":"来电归属地+黑白名单 专业版","company":"Kevin Fingster","category":"Utilities"},{"order":14,"name":"植物大战僵尸","company":"","category":""},{"order":15,"name":"解救美女","company":"Tao Sui","category":"Games"},{"order":16,"name":"铡刀大战僵尸","company":"tao sui","category":"Games"},{"order":17,"name":"StackerGame","company":"YAPING HAN","category":"Games"},{"order":18,"name":"Flick Beetle","company":"Wang Xiaodan","category":"Games"},{"order":19,"name":"PopStar!","company":"Sang-hyun Baek","category":"Games"},{"order":20,"name":"Temple Run: 勇敢传说","company":"Walt Disney","category":"Games"},{"order":21,"name":"高德导航HD Autonavi Navigation","company":"AutoNavi Information Technology Co. Ltd.","category":"Navigation"},{"order":22,"name":"九宫格输入法","company":"Zhang Jianhua","category":"Productivity"},{"order":23,"name":"WhatsApp Messenger","company":"WhatsApp Inc.","category":"Social Networking"},{"order":24,"name":"WeicoPro 微博客户端","company":"Ricky Xu","category":"Social Networking"},{"order":25,"name":"来电归属地+黑白名单","company":"Mimi Nancy","category":"Utilities"}]},"ipad":{"paid":[{"order":1,"name":"Angry Birds Star Wars HD","company":"Rovio Entertainment Ltd","category":"Games"},{"order":2,"name":"星际塔防2 HD","company":"","category":""},{"order":3,"name":"捕鱼大亨2-联机对战版HD","company":"Clifree Technology Limited","category":"Games"},{"order":4,"name":"Office办公助手 - 多功能一体式移动办公","company":"Beijing Elinasoft Technologies Company Limited","category":"Productivity"},{"order":5,"name":"砖块之谜HD","company":"Wang Xiaodan","category":"Games"},{"order":6,"name":"鳄鱼小顽皮爱洗澡","company":"Walt Disney","category":"Games"},{"order":7,"name":"熟睡!(100%深度睡眠)","company":"","category":""},{"order":8,"name":"宠物猎人G HD","company":"","category":""},{"order":9,"name":"植物大战僵尸 HD版","company":"","category":""},{"order":10,"name":"愤怒的瓢虫HD","company":"Wang Xiaodan","category":"Games"},{"order":11,"name":"狂野飙车7：极速热力","company":"Gameloft S.A.","category":"Games"},{"order":12,"name":"Fruit Ninja HD","company":"Halfbrick","category":"Games"},{"order":13,"name":"Angry Birds Space HD","company":"Rovio Entertainment Ltd","category":"Games"},{"order":14,"name":"怪物攻城HD","company":"Wang Xiaodan","category":"Games"},{"order":15,"name":"新概念英语全四册美音版(New Concept English)","company":"Yanfeng Wang","category":"Reference"},{"order":16,"name":"Flash视频浏览器","company":"LI SI MIN","category":"Utilities"},{"order":17,"name":"Wreck-it Ralph","company":"Walt Disney","category":"Games"},{"order":18,"name":"PopStar! HD","company":"Eliza Li","category":"Games"},{"order":19,"name":"疯狂赛马 HD","company":"","category":""},{"order":20,"name":"FT商学院","company":"Financial Times Ltd.","category":"Education"},{"order":21,"name":"WeicoPro HD 微博客户端","company":"Ricky Xu","category":"Social Networking"},{"order":22,"name":"Need for Speed™ Most Wanted","company":"","category":""},{"order":23,"name":"FIFA 13 by EA SPORTS","company":"","category":""},{"order":24,"name":"Infinity Blade II","company":"Chair Entertainment Group","category":"Games"},{"order":25,"name":"扫描全能王 - CamScanner HD Pro","company":"IntSig Information Co.,Ltd","category":"Productivity"}],"free":[{"order":1,"name":"疯狂攀岩家HD","company":"Beijing Chukong Aipu Technology Co.,Ltd.","category":"Games"},{"order":2,"name":"博雅斗地主HD(支持蓝牙)","company":"","category":""},{"order":3,"name":"快速问医生HD","company":"Beijing Tusheng Network Technology Co., Ltd.","category":"Health &amp; Fitness"},{"order":4,"name":"淘宝 HD","company":"","category":""},{"order":5,"name":"网游高清视频","company":"Shiwan.com Information Technology Co., Ltd.","category":"Entertainment"},{"order":6,"name":"三国游戏HD","company":"beijing jiqu information technology liability co.ltd","category":"Games"},{"order":7,"name":"黑色之翼.防御者-HD","company":"mingming fu","category":"Games"},{"order":8,"name":"名将-酒馆英雄HD","company":"Su Zhou Si Ji Feng Internet Information Technology Development Co.,Ltd.","category":"Games"},{"order":9,"name":"战争世界——为你的国家奋勇开战！","company":"Gameloft S.A.","category":"Games"},{"order":10,"name":"QQ HD 2012","company":"Tencent Technology(Shenzhen) Company Limited","category":"Social Networking"},{"order":11,"name":"纵横商海","company":"Shanghai Qianxiang Changda Internet Information Technology Development Co.,Ltd.","category":"Games"},{"order":12,"name":"百度HD","company":"Beijing Baidu Netcom Science &amp; Technology Co.,Ltd","category":"Utilities"},{"order":13,"name":"最畅销书籍TOP100","company":"Cuimei Fan","category":"Book"},{"order":14,"name":"3D 头像制作 - 由 BuddyPoke制作的动画表情和图片","company":"","category":""},{"order":15,"name":"PPTV网络电视 HD","company":"PPLive Corporation","category":"Entertainment"},{"order":16,"name":"奇艺高清影视-免费提供海量高清正版视频，电影、电视剧、动漫、综艺、娱乐、奥运节目","company":"Beijing Qiyi Century Science &amp; Technology Co.,LTD.","category":"Entertainment"},{"order":17,"name":"优酷HD","company":"Youku.com Inc.","category":"Entertainment"},{"order":18,"name":"全球使命","company":"","category":""},{"order":19,"name":"粘粘球 HHD","company":"Yu jiayin","category":"Games"},{"order":20,"name":"UC 浏览器(iPad版)","company":"","category":""},{"order":21,"name":"Aerox","company":"Synoptical Studios Ltd","category":"Games"},{"order":22,"name":"ZOOKEEPER BATTLE","company":"KITERETSU.INC","category":"Games"},{"order":23,"name":"微博 HD","company":"SINA Corporation (Nasdaq: SINA)","category":"Social Networking"},{"order":24,"name":"QQ音乐HD","company":"","category":""},{"order":25,"name":"Podcasts","company":"Apple Inc.","category":"Entertainment"}],"grossing":[{"order":1,"name":"龙之力量","company":"","category":""},{"order":2,"name":"神仙道","company":"PinIdea Co., Ltd.","category":"Games"},{"order":3,"name":"忘仙HD","company":"","category":""},{"order":4,"name":"富豪传奇","company":"Zhuhai KeyRun Network Technology CO.,Ltd","category":"Games"},{"order":5,"name":"雄霸天地(简体版)","company":"","category":""},{"order":6,"name":"逆转三国","company":"","category":""},{"order":7,"name":"三国来了HD","company":"Lediaitong Technology Co., Ltd.","category":"Games"},{"order":8,"name":"二战风云 HD","company":"","category":""},{"order":9,"name":"战魂Online","company":"","category":""},{"order":10,"name":"大掌门","company":"","category":""},{"order":11,"name":"将军","company":"","category":""},{"order":12,"name":"神仙道HD","company":"PinIdea Co., Ltd.","category":"Games"},{"order":13,"name":"战争世界——为你的国家奋勇开战！","company":"Gameloft S.A.","category":"Games"},{"order":14,"name":"杀手2-影子阴谋","company":"Glu Games Inc","category":"Games"},{"order":15,"name":"Clash of Clans","company":"Supercell Oy","category":"Games"},{"order":16,"name":"博雅德州扑克 HD","company":"","category":""},{"order":17,"name":"决战三国豪华版-HD","company":"","category":""},{"order":18,"name":"Angry Birds Star Wars HD","company":"Rovio Entertainment Ltd","category":"Games"},{"order":19,"name":"永恒战士2-无双战神","company":"Glu Games Inc","category":"Games"},{"order":20,"name":"植物大战僵尸 HD版","company":"","category":""},{"order":21,"name":"开心水族箱","company":"","category":""},{"order":22,"name":"捕鱼达人2 HD","company":"","category":""},{"order":23,"name":"胡莱三国 for iPad","company":"","category":""},{"order":24,"name":"德州撲克 Texas Poker","company":"KAMAGAMES LTD","category":"Games"},{"order":25,"name":"僵尸坞","company":"Gameloft S.A.","category":"Games"}]}}